[
  {
    "line": 1,
    "elements": [
      {
        "line": 3,
        "name": "",
        "description": "",
        "type": "background",
        "keyword": "Background",
        "steps": [
          {
            "result": {
              "duration": 1945000000,
              "status": "passed"
            },
            "line": 4,
            "name": "Launch specific browser",
            "match": {
              "location": "stepDefinitions.stepDefinitions.launch_specific_browser()"
            },
            "keyword": "Given "
          },
          {
            "result": {
              "duration": 1460000000,
              "status": "passed"
            },
            "line": 5,
            "name": "Open URL \"https://admin-demo.nopcommerce.com/login\"",
            "match": {
              "arguments": [
                {
                  "val": "\"https://admin-demo.nopcommerce.com/login\"",
                  "offset": 9
                }
              ],
              "location": "stepDefinitions.stepDefinitions.open_url(java.lang.String)"
            },
            "keyword": "When "
          },
          {
            "result": {
              "duration": 232000000,
              "status": "passed"
            },
            "line": 6,
            "name": "Enter email as \"admin@yourstore.com\" and password as \"admin\"",
            "match": {
              "arguments": [
                {
                  "val": "\"admin@yourstore.com\"",
                  "offset": 15
                },
                {
                  "val": "\"admin\"",
                  "offset": 53
                }
              ],
              "location": "stepDefinitions.stepDefinitions.enter_email_as_and_password_as(java.lang.String,java.lang.String)"
            },
            "keyword": "And "
          },
          {
            "result": {
              "duration": 6257000000,
              "status": "passed"
            },
            "line": 7,
            "name": "click  Login btn",
            "match": {
              "location": "stepDefinitions.stepDefinitions.click_login_btn()"
            },
            "keyword": "And "
          },
          {
            "result": {
              "duration": 19000000,
              "status": "passed"
            },
            "line": 8,
            "name": "view Dashboard",
            "match": {
              "location": "stepDefinitions.stepDefinitions.view_dashboard()"
            },
            "keyword": "Then "
          }
        ]
      },
      {
        "start_timestamp": "2021-03-28T17:38:45.735Z",
        "line": 11,
        "name": "Add New Customer",
        "description": "",
        "id": "customers;add-new-customer",
        "type": "scenario",
        "keyword": "Scenario",
        "steps": [
          {
            "result": {
              "duration": 103000000,
              "status": "passed"
            },
            "line": 12,
            "name": "click on cutomers menu",
            "match": {
              "location": "stepDefinitions.stepDefinitions.click_on_cutomers_menu()"
            },
            "keyword": "When "
          },
          {
            "result": {
              "duration": 909000000,
              "status": "passed"
            },
            "line": 13,
            "name": "click on customers menu item",
            "match": {
              "location": "stepDefinitions.stepDefinitions.click_on_customers_menu_item()"
            },
            "keyword": "And "
          },
          {
            "result": {
              "duration": 4079000000,
              "status": "passed"
            },
            "line": 14,
            "name": "click on Add new button",
            "match": {
              "location": "stepDefinitions.stepDefinitions.click_on_add_new_button()"
            },
            "keyword": "And "
          },
          {
            "result": {
              "duration": 11000000,
              "status": "passed"
            },
            "line": 15,
            "name": "view Add new customer page",
            "match": {
              "location": "stepDefinitions.stepDefinitions.view_add_new_customer_page()"
            },
            "keyword": "Then "
          },
          {
            "result": {
              "duration": 5350000000,
              "status": "passed"
            },
            "line": 16,
            "name": "enter customer informations",
            "match": {
              "location": "stepDefinitions.stepDefinitions.enter_customer_informations()"
            },
            "keyword": "When "
          },
          {
            "result": {
              "duration": 6174000000,
              "status": "passed"
            },
            "line": 17,
            "name": "click on save button",
            "match": {
              "location": "stepDefinitions.stepDefinitions.click_on_save_button()"
            },
            "keyword": "And "
          },
          {
            "result": {
              "duration": 255000000,
              "status": "passed"
            },
            "line": 18,
            "name": "verify confirmation message \"The new customer has been added successfully.\"",
            "match": {
              "arguments": [
                {
                  "val": "\"The new customer has been added successfully.\"",
                  "offset": 28
                }
              ],
              "location": "stepDefinitions.stepDefinitions.verify_confirmation_message(java.lang.String)"
            },
            "keyword": "Then "
          },
          {
            "result": {
              "duration": 4202000000,
              "status": "passed"
            },
            "line": 19,
            "name": "click logout link",
            "match": {
              "location": "stepDefinitions.stepDefinitions.click_logout_link()"
            },
            "keyword": "When "
          },
          {
            "result": {
              "duration": 42000000,
              "status": "passed"
            },
            "line": 20,
            "name": "page title should be \"Your store. Login\"",
            "match": {
              "arguments": [
                {
                  "val": "\"Your store. Login\"",
                  "offset": 21
                }
              ],
              "location": "stepDefinitions.stepDefinitions.page_title_should_be(java.lang.String)"
            },
            "keyword": "Then "
          },
          {
            "result": {
              "duration": 721000000,
              "status": "passed"
            },
            "line": 21,
            "name": "close browser",
            "match": {
              "location": "stepDefinitions.stepDefinitions.close_browser()"
            },
            "keyword": "And "
          }
        ],
        "tags": [
          {
            "name": "@sanity"
          }
        ]
      },
      {
        "line": 3,
        "name": "",
        "description": "",
        "type": "background",
        "keyword": "Background",
        "steps": [
          {
            "result": {
              "duration": 1191000000,
              "status": "passed"
            },
            "line": 4,
            "name": "Launch specific browser",
            "match": {
              "location": "stepDefinitions.stepDefinitions.launch_specific_browser()"
            },
            "keyword": "Given "
          },
          {
            "result": {
              "duration": 1588000000,
              "status": "passed"
            },
            "line": 5,
            "name": "Open URL \"https://admin-demo.nopcommerce.com/login\"",
            "match": {
              "arguments": [
                {
                  "val": "\"https://admin-demo.nopcommerce.com/login\"",
                  "offset": 9
                }
              ],
              "location": "stepDefinitions.stepDefinitions.open_url(java.lang.String)"
            },
            "keyword": "When "
          },
          {
            "result": {
              "duration": 202000000,
              "status": "passed"
            },
            "line": 6,
            "name": "Enter email as \"admin@yourstore.com\" and password as \"admin\"",
            "match": {
              "arguments": [
                {
                  "val": "\"admin@yourstore.com\"",
                  "offset": 15
                },
                {
                  "val": "\"admin\"",
                  "offset": 53
                }
              ],
              "location": "stepDefinitions.stepDefinitions.enter_email_as_and_password_as(java.lang.String,java.lang.String)"
            },
            "keyword": "And "
          },
          {
            "result": {
              "duration": 6224000000,
              "status": "passed"
            },
            "line": 7,
            "name": "click  Login btn",
            "match": {
              "location": "stepDefinitions.stepDefinitions.click_login_btn()"
            },
            "keyword": "And "
          },
          {
            "result": {
              "duration": 5000000,
              "status": "passed"
            },
            "line": 8,
            "name": "view Dashboard",
            "match": {
              "location": "stepDefinitions.stepDefinitions.view_dashboard()"
            },
            "keyword": "Then "
          }
        ]
      },
      {
        "start_timestamp": "2021-03-28T17:39:17.615Z",
        "line": 24,
        "name": "Search Customer by email",
        "description": "",
        "id": "customers;search-customer-by-email",
        "type": "scenario",
        "keyword": "Scenario",
        "steps": [
          {
            "result": {
              "duration": 81000000,
              "status": "passed"
            },
            "line": 25,
            "name": "click on cutomers menu",
            "match": {
              "location": "stepDefinitions.stepDefinitions.click_on_cutomers_menu()"
            },
            "keyword": "When "
          },
          {
            "result": {
              "duration": 1295000000,
              "status": "passed"
            },
            "line": 26,
            "name": "click on customers menu item",
            "match": {
              "location": "stepDefinitions.stepDefinitions.click_on_customers_menu_item()"
            },
            "keyword": "And "
          },
          {
            "result": {
              "duration": 113000000,
              "status": "passed"
            },
            "line": 27,
            "name": "enter customer email",
            "match": {
              "location": "stepDefinitions.stepDefinitions.enter_customer_email()"
            },
            "keyword": "When "
          },
          {
            "result": {
              "duration": 3062000000,
              "status": "passed"
            },
            "line": 28,
            "name": "click search btn",
            "match": {
              "location": "stepDefinitions.stepDefinitions.click_search_btn()"
            },
            "keyword": "Then "
          },
          {
            "result": {
              "duration": 119000000,
              "status": "passed"
            },
            "line": 29,
            "name": "validate email add in the search result table",
            "match": {
              "location": "stepDefinitions.stepDefinitions.validate_email_add_in_the_search_result_table()"
            },
            "keyword": "And "
          },
          {
            "result": {
              "duration": 4210000000,
              "status": "passed"
            },
            "line": 30,
            "name": "click logout link",
            "match": {
              "location": "stepDefinitions.stepDefinitions.click_logout_link()"
            },
            "keyword": "When "
          },
          {
            "result": {
              "duration": 37000000,
              "status": "passed"
            },
            "line": 31,
            "name": "page title should be \"Your store. Login\"",
            "match": {
              "arguments": [
                {
                  "val": "\"Your store. Login\"",
                  "offset": 21
                }
              ],
              "location": "stepDefinitions.stepDefinitions.page_title_should_be(java.lang.String)"
            },
            "keyword": "Then "
          },
          {
            "result": {
              "duration": 715000000,
              "status": "passed"
            },
            "line": 32,
            "name": "close browser",
            "match": {
              "location": "stepDefinitions.stepDefinitions.close_browser()"
            },
            "keyword": "And "
          }
        ],
        "tags": [
          {
            "name": "@regression"
          }
        ]
      },
      {
        "line": 3,
        "name": "",
        "description": "",
        "type": "background",
        "keyword": "Background",
        "steps": [
          {
            "result": {
              "duration": 1138000000,
              "status": "passed"
            },
            "line": 4,
            "name": "Launch specific browser",
            "match": {
              "location": "stepDefinitions.stepDefinitions.launch_specific_browser()"
            },
            "keyword": "Given "
          },
          {
            "result": {
              "duration": 1490000000,
              "status": "passed"
            },
            "line": 5,
            "name": "Open URL \"https://admin-demo.nopcommerce.com/login\"",
            "match": {
              "arguments": [
                {
                  "val": "\"https://admin-demo.nopcommerce.com/login\"",
                  "offset": 9
                }
              ],
              "location": "stepDefinitions.stepDefinitions.open_url(java.lang.String)"
            },
            "keyword": "When "
          },
          {
            "result": {
              "duration": 201000000,
              "status": "passed"
            },
            "line": 6,
            "name": "Enter email as \"admin@yourstore.com\" and password as \"admin\"",
            "match": {
              "arguments": [
                {
                  "val": "\"admin@yourstore.com\"",
                  "offset": 15
                },
                {
                  "val": "\"admin\"",
                  "offset": 53
                }
              ],
              "location": "stepDefinitions.stepDefinitions.enter_email_as_and_password_as(java.lang.String,java.lang.String)"
            },
            "keyword": "And "
          },
          {
            "result": {
              "duration": 4785000000,
              "status": "passed"
            },
            "line": 7,
            "name": "click  Login btn",
            "match": {
              "location": "stepDefinitions.stepDefinitions.click_login_btn()"
            },
            "keyword": "And "
          },
          {
            "result": {
              "duration": 14000000,
              "status": "passed"
            },
            "line": 8,
            "name": "view Dashboard",
            "match": {
              "location": "stepDefinitions.stepDefinitions.view_dashboard()"
            },
            "keyword": "Then "
          }
        ]
      },
      {
        "start_timestamp": "2021-03-28T17:39:36.471Z",
        "line": 35,
        "name": "Search Customer by firstname and lastname",
        "description": "",
        "id": "customers;search-customer-by-firstname-and-lastname",
        "type": "scenario",
        "keyword": "Scenario",
        "steps": [
          {
            "result": {
              "duration": 168000000,
              "status": "passed"
            },
            "line": 36,
            "name": "click on cutomers menu",
            "match": {
              "location": "stepDefinitions.stepDefinitions.click_on_cutomers_menu()"
            },
            "keyword": "When "
          },
          {
            "result": {
              "duration": 930000000,
              "status": "passed"
            },
            "line": 37,
            "name": "click on customers menu item",
            "match": {
              "location": "stepDefinitions.stepDefinitions.click_on_customers_menu_item()"
            },
            "keyword": "And "
          },
          {
            "result": {
              "duration": 84000000,
              "status": "passed"
            },
            "line": 38,
            "name": "enter customer firstname \"Victoria\"",
            "match": {
              "arguments": [
                {
                  "val": "\"Victoria\"",
                  "offset": 25
                }
              ],
              "location": "stepDefinitions.stepDefinitions.enter_customer_firstname(java.lang.String)"
            },
            "keyword": "When "
          },
          {
            "result": {
              "duration": 82000000,
              "status": "passed"
            },
            "line": 39,
            "name": "enter customer lastname \"Terces\"",
            "match": {
              "arguments": [
                {
                  "val": "\"Terces\"",
                  "offset": 24
                }
              ],
              "location": "stepDefinitions.stepDefinitions.enter_customer_lastname(java.lang.String)"
            },
            "keyword": "And "
          },
          {
            "result": {
              "duration": 3213000000,
              "status": "passed"
            },
            "line": 40,
            "name": "click search btn",
            "match": {
              "location": "stepDefinitions.stepDefinitions.click_search_btn()"
            },
            "keyword": "Then "
          },
          {
            "result": {
              "duration": 124000000,
              "status": "passed"
            },
            "line": 41,
            "name": "validate fname \"Victoria\" and lname \"Terces\" in the search result table",
            "match": {
              "arguments": [
                {
                  "val": "\"Victoria\"",
                  "offset": 15
                },
                {
                  "val": "\"Terces\"",
                  "offset": 36
                }
              ],
              "location": "stepDefinitions.stepDefinitions.validate_fname_and_lname_in_the_search_result_table(java.lang.String,java.lang.String)"
            },
            "keyword": "And "
          },
          {
            "result": {
              "duration": 3959000000,
              "status": "passed"
            },
            "line": 42,
            "name": "click logout link",
            "match": {
              "location": "stepDefinitions.stepDefinitions.click_logout_link()"
            },
            "keyword": "When "
          },
          {
            "result": {
              "duration": 43000000,
              "status": "passed"
            },
            "line": 43,
            "name": "page title should be \"Your store. Login\"",
            "match": {
              "arguments": [
                {
                  "val": "\"Your store. Login\"",
                  "offset": 21
                }
              ],
              "location": "stepDefinitions.stepDefinitions.page_title_should_be(java.lang.String)"
            },
            "keyword": "Then "
          },
          {
            "result": {
              "duration": 730000000,
              "status": "passed"
            },
            "line": 44,
            "name": "close browser",
            "match": {
              "location": "stepDefinitions.stepDefinitions.close_browser()"
            },
            "keyword": "And "
          }
        ],
        "tags": [
          {
            "name": "@regression"
          }
        ]
      }
    ],
    "name": "Customers",
    "description": "",
    "id": "customers",
    "keyword": "Feature",
    "uri": "file:Features/Customers.feature",
    "tags": []
  },
  {
    "line": 1,
    "elements": [
      {
        "start_timestamp": "2021-03-28T17:39:53.452Z",
        "line": 3,
        "name": "Successful login with valid credentials",
        "description": "",
        "id": "nopecommerce-site-login;successful-login-with-valid-credentials",
        "type": "scenario",
        "keyword": "Scenario",
        "steps": [
          {
            "result": {
              "duration": 1103000000,
              "status": "passed"
            },
            "line": 4,
            "name": "Launch specific browser",
            "match": {
              "location": "stepDefinitions.stepDefinitions.launch_specific_browser()"
            },
            "keyword": "Given "
          },
          {
            "result": {
              "duration": 1536000000,
              "status": "passed"
            },
            "line": 5,
            "name": "Open URL \"https://admin-demo.nopcommerce.com/login\"",
            "match": {
              "arguments": [
                {
                  "val": "\"https://admin-demo.nopcommerce.com/login\"",
                  "offset": 9
                }
              ],
              "location": "stepDefinitions.stepDefinitions.open_url(java.lang.String)"
            },
            "keyword": "When "
          },
          {
            "result": {
              "duration": 234000000,
              "status": "passed"
            },
            "line": 6,
            "name": "Enter email as \"admin@yourstore.com\" and password as \"admin\"",
            "match": {
              "arguments": [
                {
                  "val": "\"admin@yourstore.com\"",
                  "offset": 15
                },
                {
                  "val": "\"admin\"",
                  "offset": 53
                }
              ],
              "location": "stepDefinitions.stepDefinitions.enter_email_as_and_password_as(java.lang.String,java.lang.String)"
            },
            "keyword": "And "
          },
          {
            "result": {
              "duration": 6205000000,
              "status": "passed"
            },
            "line": 7,
            "name": "click  Login btn",
            "match": {
              "location": "stepDefinitions.stepDefinitions.click_login_btn()"
            },
            "keyword": "And "
          },
          {
            "result": {
              "duration": 72000000,
              "status": "passed"
            },
            "line": 8,
            "name": "verify that title should be \"Dashboard / nopCommerce administration\"",
            "match": {
              "arguments": [
                {
                  "val": "\"Dashboard / nopCommerce administration\"",
                  "offset": 28
                }
              ],
              "location": "stepDefinitions.stepDefinitions.verify_that_title_should_be(java.lang.String)"
            },
            "keyword": "Then "
          },
          {
            "result": {
              "duration": 4214000000,
              "status": "passed"
            },
            "line": 9,
            "name": "click logout link",
            "match": {
              "location": "stepDefinitions.stepDefinitions.click_logout_link()"
            },
            "keyword": "When "
          },
          {
            "result": {
              "duration": 22000000,
              "status": "passed"
            },
            "line": 10,
            "name": "page title should be \"Your store. Login\"",
            "match": {
              "arguments": [
                {
                  "val": "\"Your store. Login\"",
                  "offset": 21
                }
              ],
              "location": "stepDefinitions.stepDefinitions.page_title_should_be(java.lang.String)"
            },
            "keyword": "Then "
          },
          {
            "result": {
              "duration": 637000000,
              "status": "passed"
            },
            "line": 11,
            "name": "close browser",
            "match": {
              "location": "stepDefinitions.stepDefinitions.close_browser()"
            },
            "keyword": "And "
          }
        ],
        "tags": [
          {
            "name": "@sanity"
          }
        ]
      },
      {
        "start_timestamp": "2021-03-28T17:40:07.505Z",
        "line": 26,
        "name": "Login Data driven",
        "description": "",
        "id": "nopecommerce-site-login;login-data-driven;;2",
        "type": "scenario",
        "keyword": "Scenario Outline",
        "steps": [
          {
            "result": {
              "duration": 1111000000,
              "status": "passed"
            },
            "line": 15,
            "name": "Launch specific browser",
            "match": {
              "location": "stepDefinitions.stepDefinitions.launch_specific_browser()"
            },
            "keyword": "Given "
          },
          {
            "result": {
              "duration": 1260000000,
              "status": "passed"
            },
            "line": 16,
            "name": "Open URL \"https://admin-demo.nopcommerce.com/login\"",
            "match": {
              "arguments": [
                {
                  "val": "\"https://admin-demo.nopcommerce.com/login\"",
                  "offset": 9
                }
              ],
              "location": "stepDefinitions.stepDefinitions.open_url(java.lang.String)"
            },
            "keyword": "When "
          },
          {
            "result": {
              "duration": 199000000,
              "status": "passed"
            },
            "line": 17,
            "name": "Enter email as \"admin@yourstore.com\" and password as \"admin\"",
            "match": {
              "arguments": [
                {
                  "val": "\"admin@yourstore.com\"",
                  "offset": 15
                },
                {
                  "val": "\"admin\"",
                  "offset": 53
                }
              ],
              "location": "stepDefinitions.stepDefinitions.enter_email_as_and_password_as(java.lang.String,java.lang.String)"
            },
            "keyword": "And "
          },
          {
            "result": {
              "duration": 4669000000,
              "status": "passed"
            },
            "line": 18,
            "name": "click  Login btn",
            "match": {
              "location": "stepDefinitions.stepDefinitions.click_login_btn()"
            },
            "keyword": "And "
          },
          {
            "result": {
              "duration": 92000000,
              "status": "passed"
            },
            "line": 19,
            "name": "verify that title should be \"Dashboard / nopCommerce administration\"",
            "match": {
              "arguments": [
                {
                  "val": "\"Dashboard / nopCommerce administration\"",
                  "offset": 28
                }
              ],
              "location": "stepDefinitions.stepDefinitions.verify_that_title_should_be(java.lang.String)"
            },
            "keyword": "Then "
          },
          {
            "result": {
              "duration": 3902000000,
              "status": "passed"
            },
            "line": 20,
            "name": "click logout link",
            "match": {
              "location": "stepDefinitions.stepDefinitions.click_logout_link()"
            },
            "keyword": "When "
          },
          {
            "result": {
              "duration": 21000000,
              "status": "passed"
            },
            "line": 21,
            "name": "page title should be \"Your store. Login\"",
            "match": {
              "arguments": [
                {
                  "val": "\"Your store. Login\"",
                  "offset": 21
                }
              ],
              "location": "stepDefinitions.stepDefinitions.page_title_should_be(java.lang.String)"
            },
            "keyword": "Then "
          },
          {
            "result": {
              "duration": 619000000,
              "status": "passed"
            },
            "line": 22,
            "name": "close browser",
            "match": {
              "location": "stepDefinitions.stepDefinitions.close_browser()"
            },
            "keyword": "And "
          }
        ],
        "tags": [
          {
            "name": "@regression"
          }
        ]
      },
      {
        "start_timestamp": "2021-03-28T17:40:19.396Z",
        "line": 27,
        "name": "Login Data driven",
        "description": "",
        "id": "nopecommerce-site-login;login-data-driven;;3",
        "type": "scenario",
        "keyword": "Scenario Outline",
        "steps": [
          {
            "result": {
              "duration": 1096000000,
              "status": "passed"
            },
            "line": 15,
            "name": "Launch specific browser",
            "match": {
              "location": "stepDefinitions.stepDefinitions.launch_specific_browser()"
            },
            "keyword": "Given "
          },
          {
            "result": {
              "duration": 1244000000,
              "status": "passed"
            },
            "line": 16,
            "name": "Open URL \"https://admin-demo.nopcommerce.com/login\"",
            "match": {
              "arguments": [
                {
                  "val": "\"https://admin-demo.nopcommerce.com/login\"",
                  "offset": 9
                }
              ],
              "location": "stepDefinitions.stepDefinitions.open_url(java.lang.String)"
            },
            "keyword": "When "
          },
          {
            "result": {
              "duration": 206000000,
              "status": "passed"
            },
            "line": 17,
            "name": "Enter email as \"admin@yourstore.com\" and password as \"admin123\"",
            "match": {
              "arguments": [
                {
                  "val": "\"admin@yourstore.com\"",
                  "offset": 15
                },
                {
                  "val": "\"admin123\"",
                  "offset": 53
                }
              ],
              "location": "stepDefinitions.stepDefinitions.enter_email_as_and_password_as(java.lang.String,java.lang.String)"
            },
            "keyword": "And "
          },
          {
            "result": {
              "duration": 3443000000,
              "status": "passed"
            },
            "line": 18,
            "name": "click  Login btn",
            "match": {
              "location": "stepDefinitions.stepDefinitions.click_login_btn()"
            },
            "keyword": "And "
          },
          {
            "result": {
              "error_message": "java.lang.AssertionError\r\n\tat org.junit.Assert.fail(Assert.java:87)\r\n\tat org.junit.Assert.assertTrue(Assert.java:42)\r\n\tat org.junit.Assert.assertTrue(Assert.java:53)\r\n\tat stepDefinitions.stepDefinitions.verify_that_title_should_be(stepDefinitions.java:69)\r\n\tat ✽.verify that title should be \"Dashboard / nopCommerce administration\"(file:///C:/sridaran/Selenium-java/eclipse-workspace/nopCommerce-BDD/./Features/Login.feature:19)\r\n",
              "duration": 87000000,
              "status": "failed"
            },
            "line": 19,
            "name": "verify that title should be \"Dashboard / nopCommerce administration\"",
            "match": {
              "arguments": [
                {
                  "val": "\"Dashboard / nopCommerce administration\"",
                  "offset": 28
                }
              ],
              "location": "stepDefinitions.stepDefinitions.verify_that_title_should_be(java.lang.String)"
            },
            "keyword": "Then "
          },
          {
            "result": {
              "status": "skipped"
            },
            "line": 20,
            "name": "click logout link",
            "match": {
              "location": "stepDefinitions.stepDefinitions.click_logout_link()"
            },
            "keyword": "When "
          },
          {
            "result": {
              "duration": 1000000,
              "status": "skipped"
            },
            "line": 21,
            "name": "page title should be \"Your store. Login\"",
            "match": {
              "arguments": [
                {
                  "val": "\"Your store. Login\"",
                  "offset": 21
                }
              ],
              "location": "stepDefinitions.stepDefinitions.page_title_should_be(java.lang.String)"
            },
            "keyword": "Then "
          },
          {
            "result": {
              "status": "skipped"
            },
            "line": 22,
            "name": "close browser",
            "match": {
              "location": "stepDefinitions.stepDefinitions.close_browser()"
            },
            "keyword": "And "
          }
        ],
        "tags": [
          {
            "name": "@regression"
          }
        ]
      },
      {
        "start_timestamp": "2021-03-28T17:40:25.486Z",
        "line": 28,
        "name": "Login Data driven",
        "description": "",
        "id": "nopecommerce-site-login;login-data-driven;;4",
        "type": "scenario",
        "keyword": "Scenario Outline",
        "steps": [
          {
            "result": {
              "duration": 1177000000,
              "status": "passed"
            },
            "line": 15,
            "name": "Launch specific browser",
            "match": {
              "location": "stepDefinitions.stepDefinitions.launch_specific_browser()"
            },
            "keyword": "Given "
          },
          {
            "result": {
              "duration": 1206000000,
              "status": "passed"
            },
            "line": 16,
            "name": "Open URL \"https://admin-demo.nopcommerce.com/login\"",
            "match": {
              "arguments": [
                {
                  "val": "\"https://admin-demo.nopcommerce.com/login\"",
                  "offset": 9
                }
              ],
              "location": "stepDefinitions.stepDefinitions.open_url(java.lang.String)"
            },
            "keyword": "When "
          },
          {
            "result": {
              "duration": 195000000,
              "status": "passed"
            },
            "line": 17,
            "name": "Enter email as \"admin@yourstore.com\" and password as \"admin\"",
            "match": {
              "arguments": [
                {
                  "val": "\"admin@yourstore.com\"",
                  "offset": 15
                },
                {
                  "val": "\"admin\"",
                  "offset": 53
                }
              ],
              "location": "stepDefinitions.stepDefinitions.enter_email_as_and_password_as(java.lang.String,java.lang.String)"
            },
            "keyword": "And "
          },
          {
            "result": {
              "duration": 4767000000,
              "status": "passed"
            },
            "line": 18,
            "name": "click  Login btn",
            "match": {
              "location": "stepDefinitions.stepDefinitions.click_login_btn()"
            },
            "keyword": "And "
          },
          {
            "result": {
              "duration": 39000000,
              "status": "passed"
            },
            "line": 19,
            "name": "verify that title should be \"Dashboard / nopCommerce administration\"",
            "match": {
              "arguments": [
                {
                  "val": "\"Dashboard / nopCommerce administration\"",
                  "offset": 28
                }
              ],
              "location": "stepDefinitions.stepDefinitions.verify_that_title_should_be(java.lang.String)"
            },
            "keyword": "Then "
          },
          {
            "result": {
              "duration": 3899000000,
              "status": "passed"
            },
            "line": 20,
            "name": "click logout link",
            "match": {
              "location": "stepDefinitions.stepDefinitions.click_logout_link()"
            },
            "keyword": "When "
          },
          {
            "result": {
              "duration": 38000000,
              "status": "passed"
            },
            "line": 21,
            "name": "page title should be \"Your store. Login\"",
            "match": {
              "arguments": [
                {
                  "val": "\"Your store. Login\"",
                  "offset": 21
                }
              ],
              "location": "stepDefinitions.stepDefinitions.page_title_should_be(java.lang.String)"
            },
            "keyword": "Then "
          },
          {
            "result": {
              "duration": 665000000,
              "status": "passed"
            },
            "line": 22,
            "name": "close browser",
            "match": {
              "location": "stepDefinitions.stepDefinitions.close_browser()"
            },
            "keyword": "And "
          }
        ],
        "tags": [
          {
            "name": "@regression"
          }
        ]
      }
    ],
    "name": "nopEcommerce site Login",
    "description": "",
    "id": "nopecommerce-site-login",
    "keyword": "Feature",
    "uri": "file:Features/Login.feature",
    "tags": []
  }
]